ibdb/__init__.py
ibdb/tables.py
ibdb/utils.py
ibdb-0.0.0a4.dist-info/LICENSE
ibdb-0.0.0a4.dist-info/METADATA
ibdb-0.0.0a4.dist-info/WHEEL
ibdb-0.0.0a4.dist-info/top_level.txt
ibdb-0.0.0a4.dist-info/RECORD
