Metadata-Version: 2.1
Name: ibdb
Version: 0.0.0a4
Summary: IB-insync to Database
Home-page: UNKNOWN
Author: driller
License: UNKNOWN
Platform: UNKNOWN
Classifier: Programming Language :: Python :: 3.6
Classifier: Programming Language :: Python :: 3.7
Requires-Python: >=3.6, !=3.0.*, !=3.1.*, !=3.2.*, !=3.3.*, !=3.4.*, !=3.5.*
Requires-Dist: ib-insync
Requires-Dist: sqlalchemy
